[
  {
    "header": "39e2fb1 - 2025-10-01 13:45:25 -0500 - 10/01/2025 13:45:25",
    "grouped": {
      "Changed_Other": [
        {
          "name": "DFStringFlagRepoGitHashDynamicString",
          "mechanism": "Stores a dynamic string related to the repository's Git hash.",
          "purpose": "Ensures players have access to the latest updates and features.",
          "freq": 198,
          "old_value": "b03ee0dfec6df41a42d641ea0bd819314959f2fa",
          "new_value": "bc003a09fd5ce8a7b7ca8a135095337d375f22ba"
        },
        {
          "name": "DFStringFlipTimeStampDynamicString",
          "mechanism": "Utilizes dynamic strings to display timestamps in a more flexible manner.",
          "purpose": "Provides players with clearer and more accurate time-related information in the game.",
          "freq": 198,
          "old_value": "10/01/2025 18:42:31",
          "new_value": "10/01/2025 18:42:48"
        },
        {
          "name": "FStringFlagRepoGitHashFastString",
          "mechanism": "Utilizes a specific string format for version control in the codebase.",
          "purpose": "Ensures players benefit from the latest updates and features more reliably.",
          "freq": 198,
          "old_value": "b03ee0dfec6df41a42d641ea0bd819314959f2fa",
          "new_value": "bc003a09fd5ce8a7b7ca8a135095337d375f22ba"
        },
        {
          "name": "FStringFlipTimeStampFastString",
          "mechanism": "Optimizes how timestamps are processed in strings.",
          "purpose": "Enhances performance when displaying time-related information in games.",
          "freq": 198,
          "old_value": "10/01/2025 18:42:31",
          "new_value": "10/01/2025 18:42:48"
        }
      ]
    }
  },
  {
    "header": "1680230 - 2025-10-01 13:43:15 -0500 - 10/01/2025 13:43:14",
    "grouped": {
      "Changed_Other": [
        {
          "name": "DFStringFlagRepoGitHashDynamicString",
          "mechanism": "Stores a dynamic string related to the repository's Git hash.",
          "purpose": "Ensures players have access to the latest updates and features.",
          "freq": 198,
          "old_value": "4b41017313fefc8569989b4a001d4bf0df4208ea",
          "new_value": "b03ee0dfec6df41a42d641ea0bd819314959f2fa"
        },
        {
          "name": "DFStringFlipTimeStampDynamicString",
          "mechanism": "Utilizes dynamic strings to display timestamps in a more flexible manner.",
          "purpose": "Provides players with clearer and more accurate time-related information in the game.",
          "freq": 198,
          "old_value": "10/01/2025 18:38:17",
          "new_value": "10/01/2025 18:42:31"
        },
        {
          "name": "FStringFlagRepoGitHashFastString",
          "mechanism": "Utilizes a specific string format for version control in the codebase.",
          "purpose": "Ensures players benefit from the latest updates and features more reliably.",
          "freq": 198,
          "old_value": "4b41017313fefc8569989b4a001d4bf0df4208ea",
          "new_value": "b03ee0dfec6df41a42d641ea0bd819314959f2fa"
        },
        {
          "name": "FStringFlipTimeStampFastString",
          "mechanism": "Optimizes how timestamps are processed in strings.",
          "purpose": "Enhances performance when displaying time-related information in games.",
          "freq": 198,
          "old_value": "10/01/2025 18:38:17",
          "new_value": "10/01/2025 18:42:31"
        }
      ]
    }
  },
  {
    "header": "048901d - 2025-10-01 13:38:47 -0500 - 10/01/2025 13:38:47",
    "grouped": {
      "Added_Other": [
        {
          "name": "FFlagAXExtendUndoRedoTracking_Staged",
          "mechanism": "Enhances the tracking system for undo and redo actions in the game editor.",
          "purpose": "Allows players to better manage their changes, making it easier to revert or reapply actions.",
          "freq": 2,
          "old_value": null,
          "new_value": "true;SteadyState;10;15;Rollout;100;30;SteadyState;100;15;Promote;true;1740528363;2025-10-01T18:35:53"
        },
        {
          "name": "FFlagAXInventoryItemCardPerf_Staged",
          "mechanism": "Improves the performance of inventory item cards by optimizing how they are loaded and displayed.",
          "purpose": "Players experience faster loading times and smoother interactions with their inventory items.",
          "freq": 2,
          "old_value": null,
          "new_value": "true;SteadyState;10;15;Rollout;100;30;SteadyState;100;15;Promote;true;1740528363;2025-10-01T18:35:53"
        },
        {
          "name": "FFlagAXSlotsInventoryLoadableGridView_Staged",
          "mechanism": "Enables a new grid view layout for inventory items that can be loaded dynamically.",
          "purpose": "Provides a more organized and visually appealing way to view inventory items.",
          "freq": 2,
          "old_value": null,
          "new_value": "true;SteadyState;10;15;Rollout;100;30;SteadyState;100;15;Promote;true;1740528363;2025-10-01T18:35:53"
        }
      ],
      "Changed_Other": [
        {
          "name": "DFStringFlagRepoGitHashDynamicString",
          "mechanism": "Stores a dynamic string related to the repository's Git hash.",
          "purpose": "Ensures players have access to the latest updates and features.",
          "freq": 198,
          "old_value": "59424e006ad6cf6782dc720619e53b675149ad42",
          "new_value": "4b41017313fefc8569989b4a001d4bf0df4208ea"
        },
        {
          "name": "DFStringFlipTimeStampDynamicString",
          "mechanism": "Utilizes dynamic strings to display timestamps in a more flexible manner.",
          "purpose": "Provides players with clearer and more accurate time-related information in the game.",
          "freq": 198,
          "old_value": "10/01/2025 18:34:14",
          "new_value": "10/01/2025 18:38:17"
        },
        {
          "name": "FStringFlagRepoGitHashFastString",
          "mechanism": "Utilizes a specific string format for version control in the codebase.",
          "purpose": "Ensures players benefit from the latest updates and features more reliably.",
          "freq": 198,
          "old_value": "59424e006ad6cf6782dc720619e53b675149ad42",
          "new_value": "4b41017313fefc8569989b4a001d4bf0df4208ea"
        },
        {
          "name": "FStringFlipTimeStampFastString",
          "mechanism": "Optimizes how timestamps are processed in strings.",
          "purpose": "Enhances performance when displaying time-related information in games.",
          "freq": 198,
          "old_value": "10/01/2025 18:34:14",
          "new_value": "10/01/2025 18:38:17"
        }
      ]
    }
  },
  {
    "header": "12d1290 - 2025-10-01 13:36:37 -0500 - 10/01/2025 13:36:36",
    "grouped": {
      "Changed_Other": [
        {
          "name": "DFStringFlagRepoGitHashDynamicString",
          "mechanism": "Stores a dynamic string related to the repository's Git hash.",
          "purpose": "Ensures players have access to the latest updates and features.",
          "freq": 198,
          "old_value": "da2fc84b48e74a3ceeca567be495735caa776769",
          "new_value": "59424e006ad6cf6782dc720619e53b675149ad42"
        },
        {
          "name": "DFStringFlipTimeStampDynamicString",
          "mechanism": "Utilizes dynamic strings to display timestamps in a more flexible manner.",
          "purpose": "Provides players with clearer and more accurate time-related information in the game.",
          "freq": 198,
          "old_value": "10/01/2025 18:33:57",
          "new_value": "10/01/2025 18:34:14"
        },
        {
          "name": "FStringFlagRepoGitHashFastString",
          "mechanism": "Utilizes a specific string format for version control in the codebase.",
          "purpose": "Ensures players benefit from the latest updates and features more reliably.",
          "freq": 198,
          "old_value": "da2fc84b48e74a3ceeca567be495735caa776769",
          "new_value": "59424e006ad6cf6782dc720619e53b675149ad42"
        },
        {
          "name": "FStringFlipTimeStampFastString",
          "mechanism": "Optimizes how timestamps are processed in strings.",
          "purpose": "Enhances performance when displaying time-related information in games.",
          "freq": 198,
          "old_value": "10/01/2025 18:33:57",
          "new_value": "10/01/2025 18:34:14"
        }
      ]
    }
  },
  {
    "header": "d795897 - 2025-10-01 13:34:26 -0500 - 10/01/2025 13:34:26",
    "grouped": {
      "Added_Other": [
        {
          "name": "FFlagIEMFocusNavToButtons_Staged",
          "mechanism": "Changes how focus navigation works for buttons in Internet Explorer mode.",
          "purpose": "Makes it easier for players to navigate and interact with buttons.",
          "freq": 2,
          "old_value": null,
          "new_value": "true;SteadyState;10;15;Rollout;100;30;SteadyState;100;15;Promote;2025-10-01T18:25:24"
        }
      ],
      "Changed_Other": [
        {
          "name": "DFStringFlagRepoGitHashDynamicString",
          "mechanism": "Stores a dynamic string related to the repository's Git hash.",
          "purpose": "Ensures players have access to the latest updates and features.",
          "freq": 198,
          "old_value": "a901523c1eee418ac226652b49c5b1996b27cfe6",
          "new_value": "da2fc84b48e74a3ceeca567be495735caa776769"
        },
        {
          "name": "DFStringFlipTimeStampDynamicString",
          "mechanism": "Utilizes dynamic strings to display timestamps in a more flexible manner.",
          "purpose": "Provides players with clearer and more accurate time-related information in the game.",
          "freq": 198,
          "old_value": "10/01/2025 18:29:13",
          "new_value": "10/01/2025 18:33:57"
        },
        {
          "name": "FStringFlagRepoGitHashFastString",
          "mechanism": "Utilizes a specific string format for version control in the codebase.",
          "purpose": "Ensures players benefit from the latest updates and features more reliably.",
          "freq": 198,
          "old_value": "a901523c1eee418ac226652b49c5b1996b27cfe6",
          "new_value": "da2fc84b48e74a3ceeca567be495735caa776769"
        },
        {
          "name": "FStringFlipTimeStampFastString",
          "mechanism": "Optimizes how timestamps are processed in strings.",
          "purpose": "Enhances performance when displaying time-related information in games.",
          "freq": 198,
          "old_value": "10/01/2025 18:29:13",
          "new_value": "10/01/2025 18:33:57"
        }
      ]
    }
  },
  {
    "header": "a728c73 - 2025-10-01 13:30:03 -0500 - 10/01/2025 13:30:03",
    "grouped": {
      "Added_Other": [
        {
          "name": "DFFlagVideoCaptureBlockWinOpenGL_Staged",
          "mechanism": "Blocks video capture functionality when using OpenGL on Windows.",
          "purpose": "Prevents potential issues and crashes during video capture for Windows users.",
          "freq": 2,
          "old_value": null,
          "new_value": "true;SteadyState;10;15;Rollout;100;30;SteadyState;100;15;Promote;2025-10-01T18:20:34"
        }
      ],
      "Changed_Other": [
        {
          "name": "DFStringFlagRepoGitHashDynamicString",
          "mechanism": "Stores a dynamic string related to the repository's Git hash.",
          "purpose": "Ensures players have access to the latest updates and features.",
          "freq": 198,
          "old_value": "9780d142fa236101927deb873756278c51e2906c",
          "new_value": "a901523c1eee418ac226652b49c5b1996b27cfe6"
        },
        {
          "name": "DFStringFlipTimeStampDynamicString",
          "mechanism": "Utilizes dynamic strings to display timestamps in a more flexible manner.",
          "purpose": "Provides players with clearer and more accurate time-related information in the game.",
          "freq": 198,
          "old_value": "10/01/2025 18:23:32",
          "new_value": "10/01/2025 18:29:13"
        },
        {
          "name": "FStringFlagRepoGitHashFastString",
          "mechanism": "Utilizes a specific string format for version control in the codebase.",
          "purpose": "Ensures players benefit from the latest updates and features more reliably.",
          "freq": 198,
          "old_value": "9780d142fa236101927deb873756278c51e2906c",
          "new_value": "a901523c1eee418ac226652b49c5b1996b27cfe6"
        },
        {
          "name": "FStringFlipTimeStampFastString",
          "mechanism": "Optimizes how timestamps are processed in strings.",
          "purpose": "Enhances performance when displaying time-related information in games.",
          "freq": 198,
          "old_value": "10/01/2025 18:23:32",
          "new_value": "10/01/2025 18:29:13"
        }
      ]
    }
  },
  {
    "header": "42a304d - 2025-10-01 13:25:43 -0500 - 10/01/2025 13:25:43",
    "grouped": {
      "Added_Other": [
        {
          "name": "FFlagLuaAppShowSponsoredTooltipOnConsole_Staged",
          "mechanism": "Displays a tooltip for sponsored content on console devices.",
          "purpose": "Helps players discover sponsored games or items more easily.",
          "freq": 2,
          "old_value": null,
          "new_value": "true;SteadyState;10;15;Rollout;100;30;SteadyState;100;15;Promote;2025-10-01T18:20:13"
        },
        {
          "name": "FFlagShareLinkV2FixInvalidModal_Staged",
          "mechanism": "Fixes issues with sharing links that open modals incorrectly.",
          "purpose": "Ensures players can share links that work properly, improving usability.",
          "freq": 2,
          "old_value": null,
          "new_value": "true;SteadyState;10;15;Rollout;100;30;SteadyState;100;15;Promote;true;773046941;2025-10-01T18:19:27"
        }
      ],
      "Changed_Other": [
        {
          "name": "DFStringFlagRepoGitHashDynamicString",
          "mechanism": "Stores a dynamic string related to the repository's Git hash.",
          "purpose": "Ensures players have access to the latest updates and features.",
          "freq": 198,
          "old_value": "68dcb35ea88e652f7f851dca7bea2e1c26410365",
          "new_value": "9780d142fa236101927deb873756278c51e2906c"
        },
        {
          "name": "DFStringFlipTimeStampDynamicString",
          "mechanism": "Utilizes dynamic strings to display timestamps in a more flexible manner.",
          "purpose": "Provides players with clearer and more accurate time-related information in the game.",
          "freq": 198,
          "old_value": "10/01/2025 18:22:44",
          "new_value": "10/01/2025 18:23:32"
        },
        {
          "name": "FStringFlagRepoGitHashFastString",
          "mechanism": "Utilizes a specific string format for version control in the codebase.",
          "purpose": "Ensures players benefit from the latest updates and features more reliably.",
          "freq": 198,
          "old_value": "68dcb35ea88e652f7f851dca7bea2e1c26410365",
          "new_value": "9780d142fa236101927deb873756278c51e2906c"
        },
        {
          "name": "FStringFlipTimeStampFastString",
          "mechanism": "Optimizes how timestamps are processed in strings.",
          "purpose": "Enhances performance when displaying time-related information in games.",
          "freq": 198,
          "old_value": "10/01/2025 18:22:44",
          "new_value": "10/01/2025 18:23:32"
        }
      ]
    }
  },
  {
    "header": "c841119 - 2025-10-01 13:23:30 -0500 - 10/01/2025 13:23:30",
    "grouped": {
      "Changed_Other": [
        {
          "name": "DFStringFlagRepoGitHashDynamicString",
          "mechanism": "Stores a dynamic string related to the repository's Git hash.",
          "purpose": "Ensures players have access to the latest updates and features.",
          "freq": 198,
          "old_value": "2e7ce1c2dff8125b8784701f11be1e24132780e6",
          "new_value": "68dcb35ea88e652f7f851dca7bea2e1c26410365"
        },
        {
          "name": "DFStringFlipTimeStampDynamicString",
          "mechanism": "Utilizes dynamic strings to display timestamps in a more flexible manner.",
          "purpose": "Provides players with clearer and more accurate time-related information in the game.",
          "freq": 198,
          "old_value": "10/01/2025 18:18:16",
          "new_value": "10/01/2025 18:22:44"
        },
        {
          "name": "FStringFlagRepoGitHashFastString",
          "mechanism": "Utilizes a specific string format for version control in the codebase.",
          "purpose": "Ensures players benefit from the latest updates and features more reliably.",
          "freq": 198,
          "old_value": "2e7ce1c2dff8125b8784701f11be1e24132780e6",
          "new_value": "68dcb35ea88e652f7f851dca7bea2e1c26410365"
        },
        {
          "name": "FStringFlipTimeStampFastString",
          "mechanism": "Optimizes how timestamps are processed in strings.",
          "purpose": "Enhances performance when displaying time-related information in games.",
          "freq": 198,
          "old_value": "10/01/2025 18:18:16",
          "new_value": "10/01/2025 18:22:44"
        }
      ]
    }
  },
  {
    "header": "6e8c516 - 2025-10-01 13:19:11 -0500 - 10/01/2025 13:19:11",
    "grouped": {
      "Added_Other": [
        {
          "name": "FFlagISRCacheDirtyRootToMembers_Staged",
          "mechanism": "Improves how changes in game data are tracked and updated.",
          "purpose": "Ensures players see the latest game updates more quickly and accurately.",
          "freq": 2,
          "old_value": null,
          "new_value": "false;SteadyState;10;15;Rollout;100;30;SteadyState;100;15;Promote;true;1414628523;2025-10-01T18:17:18"
        },
        {
          "name": "FIntVoiceRtcStatsContextCardinalityThreshold_Staged",
          "mechanism": "Sets a limit on the number of voice chat participants tracked for performance stats.",
          "purpose": "Ensures better performance and stability in larger voice chat groups.",
          "freq": 2,
          "old_value": null,
          "new_value": "5;SteadyState;10;15;Rollout;100;30;SteadyState;100;15;Promote;2025-10-01T18:13:50"
        }
      ],
      "Added_Input": [
        {
          "name": "FFlagTouchscreenUseTabTipKeyboard_Staged",
          "mechanism": "Enables the use of a touchscreen keyboard for input on devices with touchscreens.",
          "purpose": "Improves typing experience for players using touch devices.",
          "freq": 2,
          "old_value": null,
          "new_value": "false;SteadyState;10;15;Rollout;100;30;SteadyState;100;15;Promote;2025-10-01T18:15:35"
        },
        {
          "name": "FFlagTouchscreenUseTabTipKeyboardPCGDKOnly_Staged",
          "mechanism": "Enables a specific keyboard interface for touchscreen devices.",
          "purpose": "Provides a better typing experience for players using touchscreens on compatible devices.",
          "freq": 2,
          "old_value": null,
          "new_value": "false;SteadyState;10;15;Rollout;100;30;SteadyState;100;15;Promote;2025-10-01T18:15:23"
        }
      ],
      "Changed_Other": [
        {
          "name": "DFStringFlagRepoGitHashDynamicString",
          "mechanism": "Stores a dynamic string related to the repository's Git hash.",
          "purpose": "Ensures players have access to the latest updates and features.",
          "freq": 198,
          "old_value": "619d8b2f249b226494258b0e9528bb9dd5e6218f",
          "new_value": "2e7ce1c2dff8125b8784701f11be1e24132780e6"
        },
        {
          "name": "DFStringFlipTimeStampDynamicString",
          "mechanism": "Utilizes dynamic strings to display timestamps in a more flexible manner.",
          "purpose": "Provides players with clearer and more accurate time-related information in the game.",
          "freq": 198,
          "old_value": "10/01/2025 18:16:30",
          "new_value": "10/01/2025 18:18:16"
        },
        {
          "name": "FStringFlagRepoGitHashFastString",
          "mechanism": "Utilizes a specific string format for version control in the codebase.",
          "purpose": "Ensures players benefit from the latest updates and features more reliably.",
          "freq": 198,
          "old_value": "619d8b2f249b226494258b0e9528bb9dd5e6218f",
          "new_value": "2e7ce1c2dff8125b8784701f11be1e24132780e6"
        },
        {
          "name": "FStringFlipTimeStampFastString",
          "mechanism": "Optimizes how timestamps are processed in strings.",
          "purpose": "Enhances performance when displaying time-related information in games.",
          "freq": 198,
          "old_value": "10/01/2025 18:16:30",
          "new_value": "10/01/2025 18:18:16"
        }
      ]
    }
  },
  {
    "header": "0c0d8d2 - 2025-10-01 13:16:59 -0500 - 10/01/2025 13:16:58",
    "grouped": {
      "Added_Other": [
        {
          "name": "DFFlagEnableGetUsersPriceLevelsApi_Staged",
          "mechanism": "Activates a new API that retrieves user pricing information.",
          "purpose": "Allows developers to offer personalized pricing for players based on their status or activity.",
          "freq": 2,
          "old_value": null,
          "new_value": "true;SteadyState;10;15;Rollout;100;30;SteadyState;100;15;Promote;2025-10-01T18:12:12"
        }
      ],
      "Changed_Other": [
        {
          "name": "DFStringFlagRepoGitHashDynamicString",
          "mechanism": "Stores a dynamic string related to the repository's Git hash.",
          "purpose": "Ensures players have access to the latest updates and features.",
          "freq": 198,
          "old_value": "3345ce70cc2cb90d8acd73d014958e18dc026255",
          "new_value": "619d8b2f249b226494258b0e9528bb9dd5e6218f"
        },
        {
          "name": "DFStringFlipTimeStampDynamicString",
          "mechanism": "Utilizes dynamic strings to display timestamps in a more flexible manner.",
          "purpose": "Provides players with clearer and more accurate time-related information in the game.",
          "freq": 198,
          "old_value": "10/01/2025 18:13:02",
          "new_value": "10/01/2025 18:16:30"
        },
        {
          "name": "FStringFlagRepoGitHashFastString",
          "mechanism": "Utilizes a specific string format for version control in the codebase.",
          "purpose": "Ensures players benefit from the latest updates and features more reliably.",
          "freq": 198,
          "old_value": "3345ce70cc2cb90d8acd73d014958e18dc026255",
          "new_value": "619d8b2f249b226494258b0e9528bb9dd5e6218f"
        },
        {
          "name": "FStringFlipTimeStampFastString",
          "mechanism": "Optimizes how timestamps are processed in strings.",
          "purpose": "Enhances performance when displaying time-related information in games.",
          "freq": 198,
          "old_value": "10/01/2025 18:13:02",
          "new_value": "10/01/2025 18:16:30"
        }
      ]
    }
  },
  {
    "header": "9a1bedd - 2025-10-01 13:14:48 -0500 - 10/01/2025 13:14:48",
    "grouped": {
      "Added_Other": [
        {
          "name": "FFlagTokenizeUnibarConstantsWithStyleProvider_Staged",
          "mechanism": "Integrates style constants into the user interface dynamically.",
          "purpose": "Enhances the visual consistency of the user interface for a better player experience.",
          "freq": 2,
          "old_value": null,
          "new_value": "true;SteadyState;10;15;Rollout;100;30;SteadyState;100;15;Promote;2025-10-01T18:09:54"
        }
      ],
      "Changed_Other": [
        {
          "name": "DFStringFlagRepoGitHashDynamicString",
          "mechanism": "Stores a dynamic string related to the repository's Git hash.",
          "purpose": "Ensures players have access to the latest updates and features.",
          "freq": 198,
          "old_value": "495c8529cbaaeef3e64355a338ed8325bfa20fb9",
          "new_value": "3345ce70cc2cb90d8acd73d014958e18dc026255"
        },
        {
          "name": "DFStringFlipTimeStampDynamicString",
          "mechanism": "Utilizes dynamic strings to display timestamps in a more flexible manner.",
          "purpose": "Provides players with clearer and more accurate time-related information in the game.",
          "freq": 198,
          "old_value": "10/01/2025 18:12:15",
          "new_value": "10/01/2025 18:13:02"
        },
        {
          "name": "FStringFlagRepoGitHashFastString",
          "mechanism": "Utilizes a specific string format for version control in the codebase.",
          "purpose": "Ensures players benefit from the latest updates and features more reliably.",
          "freq": 198,
          "old_value": "495c8529cbaaeef3e64355a338ed8325bfa20fb9",
          "new_value": "3345ce70cc2cb90d8acd73d014958e18dc026255"
        },
        {
          "name": "FStringFlipTimeStampFastString",
          "mechanism": "Optimizes how timestamps are processed in strings.",
          "purpose": "Enhances performance when displaying time-related information in games.",
          "freq": 198,
          "old_value": "10/01/2025 18:12:15",
          "new_value": "10/01/2025 18:13:02"
        }
      ]
    }
  },
  {
    "header": "f83dce7 - 2025-10-01 13:12:38 -0500 - 10/01/2025 13:12:38",
    "grouped": {
      "Changed_Other": [
        {
          "name": "DFStringFlagRepoGitHashDynamicString",
          "mechanism": "Stores a dynamic string related to the repository's Git hash.",
          "purpose": "Ensures players have access to the latest updates and features.",
          "freq": 198,
          "old_value": "bb9d22b23b771f6e1a0fa867c18561a5fec60721",
          "new_value": "495c8529cbaaeef3e64355a338ed8325bfa20fb9"
        },
        {
          "name": "DFStringFlipTimeStampDynamicString",
          "mechanism": "Utilizes dynamic strings to display timestamps in a more flexible manner.",
          "purpose": "Provides players with clearer and more accurate time-related information in the game.",
          "freq": 198,
          "old_value": "10/01/2025 18:10:11",
          "new_value": "10/01/2025 18:12:15"
        },
        {
          "name": "FStringFlagRepoGitHashFastString",
          "mechanism": "Utilizes a specific string format for version control in the codebase.",
          "purpose": "Ensures players benefit from the latest updates and features more reliably.",
          "freq": 198,
          "old_value": "bb9d22b23b771f6e1a0fa867c18561a5fec60721",
          "new_value": "495c8529cbaaeef3e64355a338ed8325bfa20fb9"
        },
        {
          "name": "FStringFlipTimeStampFastString",
          "mechanism": "Optimizes how timestamps are processed in strings.",
          "purpose": "Enhances performance when displaying time-related information in games.",
          "freq": 198,
          "old_value": "10/01/2025 18:10:11",
          "new_value": "10/01/2025 18:12:15"
        }
      ]
    }
  },
  {
    "header": "49487bd - 2025-10-01 13:10:28 -0500 - 10/01/2025 13:10:27",
    "grouped": {
      "Changed_Other": [
        {
          "name": "DFStringFlagRepoGitHashDynamicString",
          "mechanism": "Stores a dynamic string related to the repository's Git hash.",
          "purpose": "Ensures players have access to the latest updates and features.",
          "freq": 198,
          "old_value": "fc2ecdcf4a214640fb5ab3b9a056071f009a6ffc",
          "new_value": "bb9d22b23b771f6e1a0fa867c18561a5fec60721"
        },
        {
          "name": "DFStringFlipTimeStampDynamicString",
          "mechanism": "Utilizes dynamic strings to display timestamps in a more flexible manner.",
          "purpose": "Provides players with clearer and more accurate time-related information in the game.",
          "freq": 198,
          "old_value": "10/01/2025 18:06:54",
          "new_value": "10/01/2025 18:10:11"
        },
        {
          "name": "FStringFlagRepoGitHashFastString",
          "mechanism": "Utilizes a specific string format for version control in the codebase.",
          "purpose": "Ensures players benefit from the latest updates and features more reliably.",
          "freq": 198,
          "old_value": "fc2ecdcf4a214640fb5ab3b9a056071f009a6ffc",
          "new_value": "bb9d22b23b771f6e1a0fa867c18561a5fec60721"
        },
        {
          "name": "FStringFlipTimeStampFastString",
          "mechanism": "Optimizes how timestamps are processed in strings.",
          "purpose": "Enhances performance when displaying time-related information in games.",
          "freq": 198,
          "old_value": "10/01/2025 18:06:54",
          "new_value": "10/01/2025 18:10:11"
        }
      ]
    }
  },
  {
    "header": "20b27ca - 2025-10-01 13:08:14 -0500 - 10/01/2025 13:08:14",
    "grouped": {
      "Added_Other": [
        {
          "name": "FFlagSocialCarouselEnableUserSeenEvents_Staged",
          "mechanism": "Enables tracking of user interactions with social events in the carousel.",
          "purpose": "Improves user experience by showing relevant social events based on what players have already seen.",
          "freq": 2,
          "old_value": null,
          "new_value": "true;SteadyState;10;15;Rollout;100;30;SteadyState;100;15;Promote;2025-10-01T18:04:32"
        }
      ],
      "Changed_Other": [
        {
          "name": "DFStringFlagRepoGitHashDynamicString",
          "mechanism": "Stores a dynamic string related to the repository's Git hash.",
          "purpose": "Ensures players have access to the latest updates and features.",
          "freq": 198,
          "old_value": "91f5105b281fc7e38de1e03f8094bcb650973559",
          "new_value": "fc2ecdcf4a214640fb5ab3b9a056071f009a6ffc"
        },
        {
          "name": "DFStringFlipTimeStampDynamicString",
          "mechanism": "Utilizes dynamic strings to display timestamps in a more flexible manner.",
          "purpose": "Provides players with clearer and more accurate time-related information in the game.",
          "freq": 198,
          "old_value": "10/01/2025 17:59:57",
          "new_value": "10/01/2025 18:06:54"
        },
        {
          "name": "FStringFlagRepoGitHashFastString",
          "mechanism": "Utilizes a specific string format for version control in the codebase.",
          "purpose": "Ensures players benefit from the latest updates and features more reliably.",
          "freq": 198,
          "old_value": "91f5105b281fc7e38de1e03f8094bcb650973559",
          "new_value": "fc2ecdcf4a214640fb5ab3b9a056071f009a6ffc"
        },
        {
          "name": "FStringFlipTimeStampFastString",
          "mechanism": "Optimizes how timestamps are processed in strings.",
          "purpose": "Enhances performance when displaying time-related information in games.",
          "freq": 198,
          "old_value": "10/01/2025 17:59:57",
          "new_value": "10/01/2025 18:06:54"
        }
      ]
    }
  },
  {
    "header": "9f9b8a5 - 2025-10-01 13:01:46 -0500 - 10/01/2025 13:01:46",
    "grouped": {
      "Added_Other": [
        {
          "name": "FFlagEnableMultiAbuseTypeDescription_Staged",
          "mechanism": "Enables multiple descriptions for abuse types in the system.",
          "purpose": "Helps players understand different types of abuse more clearly.",
          "freq": 2,
          "old_value": null,
          "new_value": "true;SteadyState;10;15;Rollout;100;30;SteadyState;100;15;Promote;2025-10-01T17:57:29"
        }
      ],
      "Changed_Other": [
        {
          "name": "DFStringFlagRepoGitHashDynamicString",
          "mechanism": "Stores a dynamic string related to the repository's Git hash.",
          "purpose": "Ensures players have access to the latest updates and features.",
          "freq": 198,
          "old_value": "e58043d71187093a514130ff6535a75bf5bf29b2",
          "new_value": "91f5105b281fc7e38de1e03f8094bcb650973559"
        },
        {
          "name": "DFStringFlipTimeStampDynamicString",
          "mechanism": "Utilizes dynamic strings to display timestamps in a more flexible manner.",
          "purpose": "Provides players with clearer and more accurate time-related information in the game.",
          "freq": 198,
          "old_value": "10/01/2025 17:57:53",
          "new_value": "10/01/2025 17:59:57"
        },
        {
          "name": "FStringFlagRepoGitHashFastString",
          "mechanism": "Utilizes a specific string format for version control in the codebase.",
          "purpose": "Ensures players benefit from the latest updates and features more reliably.",
          "freq": 198,
          "old_value": "e58043d71187093a514130ff6535a75bf5bf29b2",
          "new_value": "91f5105b281fc7e38de1e03f8094bcb650973559"
        },
        {
          "name": "FStringFlipTimeStampFastString",
          "mechanism": "Optimizes how timestamps are processed in strings.",
          "purpose": "Enhances performance when displaying time-related information in games.",
          "freq": 198,
          "old_value": "10/01/2025 17:57:53",
          "new_value": "10/01/2025 17:59:57"
        }
      ]
    }
  },
  {
    "header": "eef7f4c - 2025-10-01 12:59:33 -0500 - 10/01/2025 12:59:33",
    "grouped": {
      "Changed_Other": [
        {
          "name": "DFStringFlagRepoGitHashDynamicString",
          "mechanism": "Stores a dynamic string related to the repository's Git hash.",
          "purpose": "Ensures players have access to the latest updates and features.",
          "freq": 198,
          "old_value": "5b4a1022943bc55ebf6f0afdc53d3450a2aa2ac6",
          "new_value": "e58043d71187093a514130ff6535a75bf5bf29b2"
        },
        {
          "name": "DFStringFlipTimeStampDynamicString",
          "mechanism": "Utilizes dynamic strings to display timestamps in a more flexible manner.",
          "purpose": "Provides players with clearer and more accurate time-related information in the game.",
          "freq": 198,
          "old_value": "10/01/2025 17:54:21",
          "new_value": "10/01/2025 17:57:53"
        },
        {
          "name": "FStringFlagRepoGitHashFastString",
          "mechanism": "Utilizes a specific string format for version control in the codebase.",
          "purpose": "Ensures players benefit from the latest updates and features more reliably.",
          "freq": 198,
          "old_value": "5b4a1022943bc55ebf6f0afdc53d3450a2aa2ac6",
          "new_value": "e58043d71187093a514130ff6535a75bf5bf29b2"
        },
        {
          "name": "FStringFlipTimeStampFastString",
          "mechanism": "Optimizes how timestamps are processed in strings.",
          "purpose": "Enhances performance when displaying time-related information in games.",
          "freq": 198,
          "old_value": "10/01/2025 17:54:21",
          "new_value": "10/01/2025 17:57:53"
        }
      ]
    }
  },
  {
    "header": "0cd9f5d - 2025-10-01 12:55:11 -0500 - 10/01/2025 12:55:11",
    "grouped": {
      "Added_Other": [
        {
          "name": "DFFlagFlagRolloutTestDynamicBool21_Staged",
          "mechanism": "Tests a dynamic boolean flag for feature rollout.",
          "purpose": "Helps in evaluating new features and their impact on player experience.",
          "freq": 2,
          "old_value": null,
          "new_value": "true;SteadyState;10;15;Rollout;100;30;SteadyState;100;15;Promote;2025-10-01T17:51:32"
        }
      ],
      "Changed_Other": [
        {
          "name": "DFStringFlagRepoGitHashDynamicString",
          "mechanism": "Stores a dynamic string related to the repository's Git hash.",
          "purpose": "Ensures players have access to the latest updates and features.",
          "freq": 198,
          "old_value": "5bd5fdf4415a748d7f5d3062a25430ce2dd9f33a",
          "new_value": "5b4a1022943bc55ebf6f0afdc53d3450a2aa2ac6"
        },
        {
          "name": "DFStringFlipTimeStampDynamicString",
          "mechanism": "Utilizes dynamic strings to display timestamps in a more flexible manner.",
          "purpose": "Provides players with clearer and more accurate time-related information in the game.",
          "freq": 198,
          "old_value": "10/01/2025 17:52:08",
          "new_value": "10/01/2025 17:54:21"
        },
        {
          "name": "FStringFlagRepoGitHashFastString",
          "mechanism": "Utilizes a specific string format for version control in the codebase.",
          "purpose": "Ensures players benefit from the latest updates and features more reliably.",
          "freq": 198,
          "old_value": "5bd5fdf4415a748d7f5d3062a25430ce2dd9f33a",
          "new_value": "5b4a1022943bc55ebf6f0afdc53d3450a2aa2ac6"
        },
        {
          "name": "FStringFlipTimeStampFastString",
          "mechanism": "Optimizes how timestamps are processed in strings.",
          "purpose": "Enhances performance when displaying time-related information in games.",
          "freq": 198,
          "old_value": "10/01/2025 17:52:08",
          "new_value": "10/01/2025 17:54:21"
        }
      ]
    }
  },
  {
    "header": "346e2ad - 2025-10-01 12:52:59 -0500 - 10/01/2025 12:52:58",
    "grouped": {
      "Added_Other": [
        {
          "name": "FFlagAddTrustedConnectionLabel_Staged",
          "mechanism": "Adds a label to indicate trusted connections in the system.",
          "purpose": "Increases player trust by clearly marking secure connections.",
          "freq": 2,
          "old_value": null,
          "new_value": "true;SteadyState;10;15;Rollout;100;30;SteadyState;100;15;Promote;2025-10-01T17:48:46"
        }
      ],
      "Changed_Other": [
        {
          "name": "DFStringFlagRepoGitHashDynamicString",
          "mechanism": "Stores a dynamic string related to the repository's Git hash.",
          "purpose": "Ensures players have access to the latest updates and features.",
          "freq": 198,
          "old_value": "20c6e09d21d6acb2e5183020f7db8a7d9fd45a48",
          "new_value": "5bd5fdf4415a748d7f5d3062a25430ce2dd9f33a"
        },
        {
          "name": "DFStringFlipTimeStampDynamicString",
          "mechanism": "Utilizes dynamic strings to display timestamps in a more flexible manner.",
          "purpose": "Provides players with clearer and more accurate time-related information in the game.",
          "freq": 198,
          "old_value": "10/01/2025 17:48:00",
          "new_value": "10/01/2025 17:52:08"
        },
        {
          "name": "FStringFlagRepoGitHashFastString",
          "mechanism": "Utilizes a specific string format for version control in the codebase.",
          "purpose": "Ensures players benefit from the latest updates and features more reliably.",
          "freq": 198,
          "old_value": "20c6e09d21d6acb2e5183020f7db8a7d9fd45a48",
          "new_value": "5bd5fdf4415a748d7f5d3062a25430ce2dd9f33a"
        },
        {
          "name": "FStringFlipTimeStampFastString",
          "mechanism": "Optimizes how timestamps are processed in strings.",
          "purpose": "Enhances performance when displaying time-related information in games.",
          "freq": 198,
          "old_value": "10/01/2025 17:48:00",
          "new_value": "10/01/2025 17:52:08"
        }
      ]
    }
  },
  {
    "header": "45975be - 2025-10-01 12:48:41 -0500 - 10/01/2025 12:48:41",
    "grouped": {
      "Added_Camera/UI": [
        {
          "name": "FFlagSTUDIOPLAT40790QuickOpenContextMenuWindowsClose_Staged",
          "mechanism": "Enhances the context menu in Studio for quicker access to close windows.",
          "purpose": "Allows developers to close windows more efficiently, improving workflow.",
          "freq": 2,
          "old_value": null,
          "new_value": "true;SteadyState;10;15;Rollout;100;30;SteadyState;100;15;Promote;2025-10-01T17:42:57"
        }
      ],
      "Added_Other": [
        {
          "name": "FFlagSwitchIsEconomicRestrictionResponse_Staged",
          "mechanism": "Modifies how economic restrictions are communicated in the game.",
          "purpose": "Provides clearer feedback to players regarding in-game economic limitations, improving user understanding.",
          "freq": 2,
          "old_value": null,
          "new_value": "true;SteadyState;10;15;Rollout;100;30;SteadyState;100;15;Promote;2025-10-01T17:45:39"
        }
      ],
      "Changed_Other": [
        {
          "name": "DFStringFlagRepoGitHashDynamicString",
          "mechanism": "Stores a dynamic string related to the repository's Git hash.",
          "purpose": "Ensures players have access to the latest updates and features.",
          "freq": 198,
          "old_value": "99c92791ac7032f238ad8378a8f30d294567e100",
          "new_value": "20c6e09d21d6acb2e5183020f7db8a7d9fd45a48"
        },
        {
          "name": "DFStringFlipTimeStampDynamicString",
          "mechanism": "Utilizes dynamic strings to display timestamps in a more flexible manner.",
          "purpose": "Provides players with clearer and more accurate time-related information in the game.",
          "freq": 198,
          "old_value": "10/01/2025 17:44:05",
          "new_value": "10/01/2025 17:48:00"
        },
        {
          "name": "FStringFlagRepoGitHashFastString",
          "mechanism": "Utilizes a specific string format for version control in the codebase.",
          "purpose": "Ensures players benefit from the latest updates and features more reliably.",
          "freq": 198,
          "old_value": "99c92791ac7032f238ad8378a8f30d294567e100",
          "new_value": "20c6e09d21d6acb2e5183020f7db8a7d9fd45a48"
        },
        {
          "name": "FStringFlipTimeStampFastString",
          "mechanism": "Optimizes how timestamps are processed in strings.",
          "purpose": "Enhances performance when displaying time-related information in games.",
          "freq": 198,
          "old_value": "10/01/2025 17:44:05",
          "new_value": "10/01/2025 17:48:00"
        }
      ]
    }
  },
  {
    "header": "5b584fa - 2025-10-01 12:46:31 -0500 - 10/01/2025 12:46:31",
    "grouped": {
      "Added_Other": [
        {
          "name": "FFlagFixiOSKeyedArchiverError_Staged",
          "mechanism": "Addresses a specific error related to data storage on iOS devices.",
          "purpose": "Ensures smoother gameplay on iOS by fixing data handling issues.",
          "freq": 2,
          "old_value": null,
          "new_value": "true;SteadyState;10;15;Rollout;100;30;SteadyState;100;15;Promote;2025-10-01T17:41:24"
        }
      ],
      "Changed_Other": [
        {
          "name": "DFStringFlagRepoGitHashDynamicString",
          "mechanism": "Stores a dynamic string related to the repository's Git hash.",
          "purpose": "Ensures players have access to the latest updates and features.",
          "freq": 198,
          "old_value": "702128b772b67df414b748e4b3b6e27e775a4173",
          "new_value": "99c92791ac7032f238ad8378a8f30d294567e100"
        },
        {
          "name": "DFStringFlipTimeStampDynamicString",
          "mechanism": "Utilizes dynamic strings to display timestamps in a more flexible manner.",
          "purpose": "Provides players with clearer and more accurate time-related information in the game.",
          "freq": 198,
          "old_value": "10/01/2025 00:43:38",
          "new_value": "10/01/2025 17:44:05"
        },
        {
          "name": "FStringFlagRepoGitHashFastString",
          "mechanism": "Utilizes a specific string format for version control in the codebase.",
          "purpose": "Ensures players benefit from the latest updates and features more reliably.",
          "freq": 198,
          "old_value": "702128b772b67df414b748e4b3b6e27e775a4173",
          "new_value": "99c92791ac7032f238ad8378a8f30d294567e100"
        },
        {
          "name": "FStringFlipTimeStampFastString",
          "mechanism": "Optimizes how timestamps are processed in strings.",
          "purpose": "Enhances performance when displaying time-related information in games.",
          "freq": 198,
          "old_value": "10/01/2025 00:43:38",
          "new_value": "10/01/2025 17:44:05"
        }
      ]
    }
  }
]