[
  {
    "header": "f94c0c8f1 - 2025-11-24 13:44:17 -0600 - 11/24/2025 13:44:16",
    "grouped": {
      "Added_Other": [
        {
          "name": "FFlagUserTileAddDataHydrationWrapper",
          "mechanism": "Adds a system to manage user data more effectively.",
          "purpose": "Provides players with a smoother experience by ensuring their data loads correctly and quickly.",
          "freq": 1,
          "old_value": null,
          "new_value": "True"
        }
      ],
      "Changed_Other": [
        {
          "name": "DFStringFlagRepoGitHashDynamicString",
          "mechanism": "Links to a dynamic string that reflects the current version of the code.",
          "purpose": "Ensures players benefit from the latest updates and fixes in the game.",
          "freq": 199,
          "old_value": "5afb36dcf9b497844062079179d3b953e6a5127d",
          "new_value": "5c6981f32609957f57d70a2ca534302eed937fc0"
        },
        {
          "name": "DFStringFlipTimeStampDynamicString",
          "mechanism": "Adjusts the way timestamps are displayed in dynamic strings.",
          "purpose": "Improves the clarity and accuracy of time-related information for players.",
          "freq": 199,
          "old_value": "11/24/2025 19:40:58",
          "new_value": "11/24/2025 19:42:20"
        },
        {
          "name": "FStringFlagRepoGitHashFastString",
          "mechanism": "Stores a fast string representation of the Git hash for version control.",
          "purpose": "Improves the speed of accessing version information for developers.",
          "freq": 199,
          "old_value": "5afb36dcf9b497844062079179d3b953e6a5127d",
          "new_value": "5c6981f32609957f57d70a2ca534302eed937fc0"
        },
        {
          "name": "FStringFlipTimeStampFastString",
          "mechanism": "Optimizes how timestamps are formatted and displayed.",
          "purpose": "Provides faster and more accurate time displays in the game.",
          "freq": 199,
          "old_value": "11/24/2025 19:40:58",
          "new_value": "11/24/2025 19:42:20"
        }
      ],
      "Removed_Other": [
        {
          "name": "FFlagUserTileAddDataHydrationWrapper_Staged",
          "mechanism": "Introduces a new method to load user profile data more efficiently.",
          "purpose": "Improves the speed and reliability of loading player profiles, enhancing user experience.",
          "freq": 2,
          "old_value": "true;SteadyState;10;15;Rollout;100;30;SteadyState;100;15;Promote;2025-11-24T18:36:36",
          "new_value": null
        }
      ]
    }
  },
  {
    "header": "9b5b59ea9 - 2025-11-24 13:41:58 -0600 - 11/24/2025 13:41:58",
    "grouped": {
      "Added_Other": [
        {
          "name": "FFlagAEGIS2UseGuacToShowEnabledMessage_Staged",
          "mechanism": "Utilizes the Guac system to display enabled messages for AEGIS2.",
          "purpose": "Provides clearer notifications to players about features being active.",
          "freq": 2,
          "old_value": null,
          "new_value": "true;SteadyState;10;15;Rollout;100;30;SteadyState;100;15;Promote;2025-11-24T19:39:46"
        }
      ],
      "Changed_Other": [
        {
          "name": "DFStringFlagRepoGitHashDynamicString",
          "mechanism": "Links to a dynamic string that reflects the current version of the code.",
          "purpose": "Ensures players benefit from the latest updates and fixes in the game.",
          "freq": 199,
          "old_value": "68bf028d574b3d26459c67d4868506ce54753f4a",
          "new_value": "5afb36dcf9b497844062079179d3b953e6a5127d"
        },
        {
          "name": "DFStringFlipTimeStampDynamicString",
          "mechanism": "Adjusts the way timestamps are displayed in dynamic strings.",
          "purpose": "Improves the clarity and accuracy of time-related information for players.",
          "freq": 199,
          "old_value": "11/24/2025 19:38:02",
          "new_value": "11/24/2025 19:40:58"
        },
        {
          "name": "FStringFlagRepoGitHashFastString",
          "mechanism": "Stores a fast string representation of the Git hash for version control.",
          "purpose": "Improves the speed of accessing version information for developers.",
          "freq": 199,
          "old_value": "68bf028d574b3d26459c67d4868506ce54753f4a",
          "new_value": "5afb36dcf9b497844062079179d3b953e6a5127d"
        },
        {
          "name": "FStringFlipTimeStampFastString",
          "mechanism": "Optimizes how timestamps are formatted and displayed.",
          "purpose": "Provides faster and more accurate time displays in the game.",
          "freq": 199,
          "old_value": "11/24/2025 19:38:02",
          "new_value": "11/24/2025 19:40:58"
        }
      ]
    }
  },
  {
    "header": "57c1d9378 - 2025-11-24 13:39:41 -0600 - 11/24/2025 13:39:40",
    "grouped": {
      "Added_Other": [
        {
          "name": "FFlagAXFixSubcategorySelectionById2",
          "mechanism": "Fixes the selection process for subcategories using IDs.",
          "purpose": "Makes it easier for players to find and select specific items or categories in the game.",
          "freq": 1,
          "old_value": null,
          "new_value": "True"
        },
        {
          "name": "FFlagIASFixResetInRollback",
          "mechanism": "Fixes an issue where certain settings reset during a rollback.",
          "purpose": "Ensures player settings remain intact even after system errors.",
          "freq": 1,
          "old_value": null,
          "new_value": "True"
        },
        {
          "name": "FFlagUnifiedPurchaseGamepassAddProductUniverseId_Staged",
          "mechanism": "Integrates product universe IDs into gamepass purchases.",
          "purpose": "Streamlines the purchasing process for gamepasses, making it easier for players to buy and access them.",
          "freq": 2,
          "old_value": null,
          "new_value": "true;SteadyState;10;15;Rollout;100;30;SteadyState;100;15;Promote;2025-11-24T19:36:56"
        }
      ],
      "Changed_Other": [
        {
          "name": "DFStringFlagRepoGitHashDynamicString",
          "mechanism": "Links to a dynamic string that reflects the current version of the code.",
          "purpose": "Ensures players benefit from the latest updates and fixes in the game.",
          "freq": 199,
          "old_value": "e37a6fdf0a995e6111df757363a76ffbe87193e8",
          "new_value": "68bf028d574b3d26459c67d4868506ce54753f4a"
        },
        {
          "name": "DFStringFlipTimeStampDynamicString",
          "mechanism": "Adjusts the way timestamps are displayed in dynamic strings.",
          "purpose": "Improves the clarity and accuracy of time-related information for players.",
          "freq": 199,
          "old_value": "11/24/2025 19:36:28",
          "new_value": "11/24/2025 19:38:02"
        },
        {
          "name": "FStringFlagRepoGitHashFastString",
          "mechanism": "Stores a fast string representation of the Git hash for version control.",
          "purpose": "Improves the speed of accessing version information for developers.",
          "freq": 199,
          "old_value": "e37a6fdf0a995e6111df757363a76ffbe87193e8",
          "new_value": "68bf028d574b3d26459c67d4868506ce54753f4a"
        },
        {
          "name": "FStringFlipTimeStampFastString",
          "mechanism": "Optimizes how timestamps are formatted and displayed.",
          "purpose": "Provides faster and more accurate time displays in the game.",
          "freq": 199,
          "old_value": "11/24/2025 19:36:28",
          "new_value": "11/24/2025 19:38:02"
        }
      ],
      "Removed_Other": [
        {
          "name": "FFlagAXFixSubcategorySelectionById2_Staged",
          "mechanism": "Fixes how subcategories are selected by their ID in the user interface.",
          "purpose": "Improves user experience by ensuring correct subcategory selections are made.",
          "freq": 2,
          "old_value": "true;SteadyState;10;15;Rollout;100;30;SteadyState;100;15;Promote;2025-11-24T18:33:45",
          "new_value": null
        },
        {
          "name": "FFlagIASFixResetInRollback_Staged",
          "mechanism": "Resets certain settings during a rollback process.",
          "purpose": "Ensures a smoother experience when reverting to previous game states.",
          "freq": 2,
          "old_value": "true;SteadyState;10;15;Rollout;100;30;SteadyState;100;15;Promote;2025-11-24T18:32:37",
          "new_value": null
        }
      ]
    }
  },
  {
    "header": "247b5e042 - 2025-11-24 13:37:22 -0600 - 11/24/2025 13:37:21",
    "grouped": {
      "Added_Other": [
        {
          "name": "DFFlagQueryRefactor_Staged",
          "mechanism": "Reworks how data queries are processed within the game.",
          "purpose": "Increases efficiency in retrieving game data for a smoother experience.",
          "freq": 2,
          "old_value": null,
          "new_value": "true;SteadyState;10;15;Rollout;100;30;SteadyState;100;15;Promote;2025-11-24T19:34:07"
        }
      ],
      "Changed_Other": [
        {
          "name": "DFStringFlagRepoGitHashDynamicString",
          "mechanism": "Links to a dynamic string that reflects the current version of the code.",
          "purpose": "Ensures players benefit from the latest updates and fixes in the game.",
          "freq": 199,
          "old_value": "9f0461046b12a7bc032050a43c5624d92ea0b651",
          "new_value": "e37a6fdf0a995e6111df757363a76ffbe87193e8"
        },
        {
          "name": "DFStringFlipTimeStampDynamicString",
          "mechanism": "Adjusts the way timestamps are displayed in dynamic strings.",
          "purpose": "Improves the clarity and accuracy of time-related information for players.",
          "freq": 199,
          "old_value": "11/24/2025 19:34:16",
          "new_value": "11/24/2025 19:36:28"
        },
        {
          "name": "FStringFlagRepoGitHashFastString",
          "mechanism": "Stores a fast string representation of the Git hash for version control.",
          "purpose": "Improves the speed of accessing version information for developers.",
          "freq": 199,
          "old_value": "9f0461046b12a7bc032050a43c5624d92ea0b651",
          "new_value": "e37a6fdf0a995e6111df757363a76ffbe87193e8"
        },
        {
          "name": "FStringFlipTimeStampFastString",
          "mechanism": "Optimizes how timestamps are formatted and displayed.",
          "purpose": "Provides faster and more accurate time displays in the game.",
          "freq": 199,
          "old_value": "11/24/2025 19:34:16",
          "new_value": "11/24/2025 19:36:28"
        }
      ]
    }
  },
  {
    "header": "e3fb04a88 - 2025-11-24 13:35:04 -0600 - 11/24/2025 13:35:04",
    "grouped": {
      "Changed_Other": [
        {
          "name": "DFStringFlagRepoGitHashDynamicString",
          "mechanism": "Links to a dynamic string that reflects the current version of the code.",
          "purpose": "Ensures players benefit from the latest updates and fixes in the game.",
          "freq": 199,
          "old_value": "9b3ffa6579723ab2e973172a5ba67b7e0dfc07ba",
          "new_value": "9f0461046b12a7bc032050a43c5624d92ea0b651"
        },
        {
          "name": "DFStringFlipTimeStampDynamicString",
          "mechanism": "Adjusts the way timestamps are displayed in dynamic strings.",
          "purpose": "Improves the clarity and accuracy of time-related information for players.",
          "freq": 199,
          "old_value": "11/24/2025 19:29:10",
          "new_value": "11/24/2025 19:34:16"
        },
        {
          "name": "FStringFlagRepoGitHashFastString",
          "mechanism": "Stores a fast string representation of the Git hash for version control.",
          "purpose": "Improves the speed of accessing version information for developers.",
          "freq": 199,
          "old_value": "9b3ffa6579723ab2e973172a5ba67b7e0dfc07ba",
          "new_value": "9f0461046b12a7bc032050a43c5624d92ea0b651"
        },
        {
          "name": "FStringFlipTimeStampFastString",
          "mechanism": "Optimizes how timestamps are formatted and displayed.",
          "purpose": "Provides faster and more accurate time displays in the game.",
          "freq": 199,
          "old_value": "11/24/2025 19:29:10",
          "new_value": "11/24/2025 19:34:16"
        }
      ]
    }
  },
  {
    "header": "78b0e2763 - 2025-11-24 13:30:15 -0600 - 11/24/2025 13:30:15",
    "grouped": {
      "Added_Other": [
        {
          "name": "FFlagFixAppInsetViewAdapterMemoryLeak",
          "mechanism": "Resolves memory leaks in the app's view adapter.",
          "purpose": "Enhances app performance by reducing memory usage.",
          "freq": 1,
          "old_value": null,
          "new_value": "True"
        },
        {
          "name": "FFlagRegisterFineGrainedAssetViews_Staged",
          "mechanism": "Implements more detailed tracking of asset views.",
          "purpose": "Provides better insights for developers on how players interact with their assets.",
          "freq": 2,
          "old_value": null,
          "new_value": "true;SteadyState;10;15;Rollout;100;30;SteadyState;100;15;Promote;2025-11-24T19:26:09"
        }
      ],
      "Changed_Other": [
        {
          "name": "DFStringFlagRepoGitHashDynamicString",
          "mechanism": "Links to a dynamic string that reflects the current version of the code.",
          "purpose": "Ensures players benefit from the latest updates and fixes in the game.",
          "freq": 199,
          "old_value": "72fef49b9cb2a6f40a3370611624df26fcfeead1",
          "new_value": "9b3ffa6579723ab2e973172a5ba67b7e0dfc07ba"
        },
        {
          "name": "DFStringFlipTimeStampDynamicString",
          "mechanism": "Adjusts the way timestamps are displayed in dynamic strings.",
          "purpose": "Improves the clarity and accuracy of time-related information for players.",
          "freq": 199,
          "old_value": "11/24/2025 19:27:43",
          "new_value": "11/24/2025 19:29:10"
        },
        {
          "name": "FFlagEnableSocialUpsellButtonMediumSize",
          "mechanism": "Changes the size of the social upsell button to medium.",
          "purpose": "Makes it easier for players to notice and access social features.",
          "freq": 1,
          "old_value": "True",
          "new_value": "False"
        },
        {
          "name": "FStringFlagRepoGitHashFastString",
          "mechanism": "Stores a fast string representation of the Git hash for version control.",
          "purpose": "Improves the speed of accessing version information for developers.",
          "freq": 199,
          "old_value": "72fef49b9cb2a6f40a3370611624df26fcfeead1",
          "new_value": "9b3ffa6579723ab2e973172a5ba67b7e0dfc07ba"
        },
        {
          "name": "FStringFlipTimeStampFastString",
          "mechanism": "Optimizes how timestamps are formatted and displayed.",
          "purpose": "Provides faster and more accurate time displays in the game.",
          "freq": 199,
          "old_value": "11/24/2025 19:27:43",
          "new_value": "11/24/2025 19:29:10"
        }
      ],
      "Removed_Other": [
        {
          "name": "FFlagEnableSocialUpsellButtonMediumSize_Staged",
          "mechanism": "Changes the size of the social upsell button to a medium size for better visibility.",
          "purpose": "Makes it easier for players to find and use social features, enhancing social interactions.",
          "freq": 2,
          "old_value": "false;SteadyState;10;15;Rollout;100;30;SteadyState;100;15;Promote;true;1940208657;2025-11-24T18:25:24",
          "new_value": null
        },
        {
          "name": "FFlagFixAppInsetViewAdapterMemoryLeak_Staged",
          "mechanism": "Fixes a memory leak in the app's view adapter.",
          "purpose": "Reduces crashes and improves app stability for players.",
          "freq": 2,
          "old_value": "true;SteadyState;10;15;Rollout;100;30;SteadyState;100;15;Promote;2025-11-24T18:22:59",
          "new_value": null
        }
      ]
    }
  },
  {
    "header": "672d8afa4 - 2025-11-24 13:27:58 -0600 - 11/24/2025 13:27:57",
    "grouped": {
      "Added_Other": [
        {
          "name": "DFFlagFlagRolloutTestDynamicBool27_Staged",
          "mechanism": "Tests a new feature by dynamically changing its availability.",
          "purpose": "Allows Roblox to experiment with features before fully launching them.",
          "freq": 2,
          "old_value": null,
          "new_value": "false;SteadyState;10;15;Rollout;100;30;SteadyState;100;15;Promote;2025-11-24T19:24:21"
        },
        {
          "name": "FFlagRegisterCallToActionView_Staged",
          "mechanism": "Enables a new interface for displaying action prompts to users.",
          "purpose": "Improves user engagement by making calls to action more visible and appealing.",
          "freq": 2,
          "old_value": null,
          "new_value": "true;SteadyState;10;15;Rollout;100;30;SteadyState;100;15;Promote;2025-11-24T19:25:47"
        },
        {
          "name": "FFlagWrapDeformerContextOutputFileMeshData5_Staged",
          "mechanism": "Enhances how mesh data is processed for deformations.",
          "purpose": "Provides smoother and more realistic animations for characters and objects.",
          "freq": 4,
          "old_value": null,
          "new_value": "true;SteadyState;10;30;Revert;2025-11-24T19:24:09"
        },
        {
          "name": "FIntIsolatedAdsBacktraceCrashUploadPercent_Staged",
          "mechanism": "Tracks and uploads crash data related to isolated ads for analysis.",
          "purpose": "Helps improve ad stability and user experience by identifying and fixing issues.",
          "freq": 2,
          "old_value": null,
          "new_value": "100;SteadyState;10;15;Rollout;100;30;SteadyState;100;15;Promote;2025-11-24T19:25:12"
        }
      ],
      "Changed_Other": [
        {
          "name": "DFStringFlagRepoGitHashDynamicString",
          "mechanism": "Links to a dynamic string that reflects the current version of the code.",
          "purpose": "Ensures players benefit from the latest updates and fixes in the game.",
          "freq": 199,
          "old_value": "007d919e50774189542040f22ca32131919ccc05",
          "new_value": "72fef49b9cb2a6f40a3370611624df26fcfeead1"
        },
        {
          "name": "DFStringFlipTimeStampDynamicString",
          "mechanism": "Adjusts the way timestamps are displayed in dynamic strings.",
          "purpose": "Improves the clarity and accuracy of time-related information for players.",
          "freq": 199,
          "old_value": "11/24/2025 19:24:12",
          "new_value": "11/24/2025 19:27:43"
        },
        {
          "name": "FStringFlagRepoGitHashFastString",
          "mechanism": "Stores a fast string representation of the Git hash for version control.",
          "purpose": "Improves the speed of accessing version information for developers.",
          "freq": 199,
          "old_value": "007d919e50774189542040f22ca32131919ccc05",
          "new_value": "72fef49b9cb2a6f40a3370611624df26fcfeead1"
        },
        {
          "name": "FStringFlipTimeStampFastString",
          "mechanism": "Optimizes how timestamps are formatted and displayed.",
          "purpose": "Provides faster and more accurate time displays in the game.",
          "freq": 199,
          "old_value": "11/24/2025 19:24:12",
          "new_value": "11/24/2025 19:27:43"
        }
      ]
    }
  },
  {
    "header": "033b8fc64 - 2025-11-24 13:25:40 -0600 - 11/24/2025 13:25:40",
    "grouped": {
      "Added_Other": [
        {
          "name": "FFlagFlagRolloutTestStaticBool34_Staged",
          "mechanism": "Activates another feature toggle for experimental testing.",
          "purpose": "Gives players access to additional features or changes in a controlled way.",
          "freq": 2,
          "old_value": null,
          "new_value": "false;SteadyState;10;15;Rollout;100;30;SteadyState;100;15;Promote;2025-11-24T19:23:10"
        },
        {
          "name": "FFlagOptInOnlyForAegis_Staged",
          "mechanism": "Restricts a feature to only users who opt-in for the Aegis system.",
          "purpose": "Allows players to choose whether to use advanced features, giving them more control over their experience.",
          "freq": 2,
          "old_value": null,
          "new_value": "true;SteadyState;10;15;Rollout;100;30;SteadyState;100;15;Promote;2025-11-24T19:22:00"
        },
        {
          "name": "FFlagSuspendOnlyForAegis_Staged",
          "mechanism": "Suspends certain processes only for the Aegis system.",
          "purpose": "Improves stability and performance for games using the Aegis system.",
          "freq": 2,
          "old_value": null,
          "new_value": "true;SteadyState;10;15;Rollout;100;30;SteadyState;100;15;Promote;2025-11-24T19:22:43"
        }
      ],
      "Changed_Other": [
        {
          "name": "DFStringFlagRepoGitHashDynamicString",
          "mechanism": "Links to a dynamic string that reflects the current version of the code.",
          "purpose": "Ensures players benefit from the latest updates and fixes in the game.",
          "freq": 199,
          "old_value": "edcf2f5f0acb7ca2905659e583ec40d2d6f676bd",
          "new_value": "007d919e50774189542040f22ca32131919ccc05"
        },
        {
          "name": "DFStringFlipTimeStampDynamicString",
          "mechanism": "Adjusts the way timestamps are displayed in dynamic strings.",
          "purpose": "Improves the clarity and accuracy of time-related information for players.",
          "freq": 199,
          "old_value": "11/24/2025 19:22:03",
          "new_value": "11/24/2025 19:24:12"
        },
        {
          "name": "FStringFlagRepoGitHashFastString",
          "mechanism": "Stores a fast string representation of the Git hash for version control.",
          "purpose": "Improves the speed of accessing version information for developers.",
          "freq": 199,
          "old_value": "edcf2f5f0acb7ca2905659e583ec40d2d6f676bd",
          "new_value": "007d919e50774189542040f22ca32131919ccc05"
        },
        {
          "name": "FStringFlipTimeStampFastString",
          "mechanism": "Optimizes how timestamps are formatted and displayed.",
          "purpose": "Provides faster and more accurate time displays in the game.",
          "freq": 199,
          "old_value": "11/24/2025 19:22:03",
          "new_value": "11/24/2025 19:24:12"
        }
      ]
    }
  },
  {
    "header": "a436e25e9 - 2025-11-24 13:23:16 -0600 - 11/24/2025 13:23:16",
    "grouped": {
      "Added_Other": [
        {
          "name": "DFFlagWindowsReduceFrameCapDuringMoveSizeLoop",
          "mechanism": "Limits the maximum frame rate during specific movement scenarios to reduce performance issues.",
          "purpose": "Improves game stability and performance on Windows devices when players are moving.",
          "freq": 1,
          "old_value": null,
          "new_value": "True"
        }
      ],
      "Changed_Other": [
        {
          "name": "DFStringFlagRepoGitHashDynamicString",
          "mechanism": "Links to a dynamic string that reflects the current version of the code.",
          "purpose": "Ensures players benefit from the latest updates and fixes in the game.",
          "freq": 199,
          "old_value": "b598c4e10b733d9be0313541fa3cba3ad20a7162",
          "new_value": "edcf2f5f0acb7ca2905659e583ec40d2d6f676bd"
        },
        {
          "name": "DFStringFlipTimeStampDynamicString",
          "mechanism": "Adjusts the way timestamps are displayed in dynamic strings.",
          "purpose": "Improves the clarity and accuracy of time-related information for players.",
          "freq": 199,
          "old_value": "11/24/2025 19:16:53",
          "new_value": "11/24/2025 19:22:03"
        },
        {
          "name": "FStringFlagRepoGitHashFastString",
          "mechanism": "Stores a fast string representation of the Git hash for version control.",
          "purpose": "Improves the speed of accessing version information for developers.",
          "freq": 199,
          "old_value": "b598c4e10b733d9be0313541fa3cba3ad20a7162",
          "new_value": "edcf2f5f0acb7ca2905659e583ec40d2d6f676bd"
        },
        {
          "name": "FStringFlipTimeStampFastString",
          "mechanism": "Optimizes how timestamps are formatted and displayed.",
          "purpose": "Provides faster and more accurate time displays in the game.",
          "freq": 199,
          "old_value": "11/24/2025 19:16:53",
          "new_value": "11/24/2025 19:22:03"
        }
      ],
      "Removed_Other": [
        {
          "name": "DFFlagWindowsReduceFrameCapDuringMoveSizeLoop_Staged",
          "mechanism": "Reduces the frame rate cap while resizing windows during specific actions.",
          "purpose": "Improves performance and responsiveness when players adjust their game window size.",
          "freq": 4,
          "old_value": "true;SteadyState;10;15;Rollout;100;30;SteadyState;100;15;Promote;2025-11-24T18:16:19",
          "new_value": null
        }
      ]
    }
  },
  {
    "header": "e158d4b74 - 2025-11-24 13:18:46 -0600 - 11/24/2025 13:18:46",
    "grouped": {
      "Changed_Other": [
        {
          "name": "DFStringFlagRepoGitHashDynamicString",
          "mechanism": "Links to a dynamic string that reflects the current version of the code.",
          "purpose": "Ensures players benefit from the latest updates and fixes in the game.",
          "freq": 199,
          "old_value": "0b481630467f10f1d2520bd219cf5b997695ce1a",
          "new_value": "b598c4e10b733d9be0313541fa3cba3ad20a7162"
        },
        {
          "name": "DFStringFlipTimeStampDynamicString",
          "mechanism": "Adjusts the way timestamps are displayed in dynamic strings.",
          "purpose": "Improves the clarity and accuracy of time-related information for players.",
          "freq": 199,
          "old_value": "11/24/2025 19:15:18",
          "new_value": "11/24/2025 19:16:53"
        },
        {
          "name": "FStringFlagRepoGitHashFastString",
          "mechanism": "Stores a fast string representation of the Git hash for version control.",
          "purpose": "Improves the speed of accessing version information for developers.",
          "freq": 199,
          "old_value": "0b481630467f10f1d2520bd219cf5b997695ce1a",
          "new_value": "b598c4e10b733d9be0313541fa3cba3ad20a7162"
        },
        {
          "name": "FStringFlipTimeStampFastString",
          "mechanism": "Optimizes how timestamps are formatted and displayed.",
          "purpose": "Provides faster and more accurate time displays in the game.",
          "freq": 199,
          "old_value": "11/24/2025 19:15:18",
          "new_value": "11/24/2025 19:16:53"
        }
      ]
    }
  },
  {
    "header": "0b77c3c18 - 2025-11-24 13:16:28 -0600 - 11/24/2025 13:16:28",
    "grouped": {
      "Added_Other": [
        {
          "name": "FFlagLuaAppFixEmptyRecommendedGames_Staged",
          "mechanism": "Fixes an issue where recommended games list appears empty.",
          "purpose": "Ensures players see game recommendations, enhancing their experience.",
          "freq": 2,
          "old_value": null,
          "new_value": "true;SteadyState;10;15;Rollout;100;30;SteadyState;100;15;Promote;2025-11-24T19:13:13"
        },
        {
          "name": "FFlagReflectBufferAsBuffer_Staged",
          "mechanism": "Changes how certain data buffers are processed and reflected in the game.",
          "purpose": "Enhances performance and visual quality for players during gameplay.",
          "freq": 2,
          "old_value": null,
          "new_value": "true;SteadyState;10;15;Rollout;100;30;SteadyState;100;15;Promote;2025-11-24T19:11:33"
        }
      ],
      "Changed_Other": [
        {
          "name": "DFStringFlagRepoGitHashDynamicString",
          "mechanism": "Links to a dynamic string that reflects the current version of the code.",
          "purpose": "Ensures players benefit from the latest updates and fixes in the game.",
          "freq": 199,
          "old_value": "485eea24389628f3c55725338dcaf95671efed56",
          "new_value": "0b481630467f10f1d2520bd219cf5b997695ce1a"
        },
        {
          "name": "DFStringFlipTimeStampDynamicString",
          "mechanism": "Adjusts the way timestamps are displayed in dynamic strings.",
          "purpose": "Improves the clarity and accuracy of time-related information for players.",
          "freq": 199,
          "old_value": "11/24/2025 19:13:22",
          "new_value": "11/24/2025 19:15:18"
        },
        {
          "name": "FStringFlagRepoGitHashFastString",
          "mechanism": "Stores a fast string representation of the Git hash for version control.",
          "purpose": "Improves the speed of accessing version information for developers.",
          "freq": 199,
          "old_value": "485eea24389628f3c55725338dcaf95671efed56",
          "new_value": "0b481630467f10f1d2520bd219cf5b997695ce1a"
        },
        {
          "name": "FStringFlipTimeStampFastString",
          "mechanism": "Optimizes how timestamps are formatted and displayed.",
          "purpose": "Provides faster and more accurate time displays in the game.",
          "freq": 199,
          "old_value": "11/24/2025 19:13:22",
          "new_value": "11/24/2025 19:15:18"
        }
      ]
    }
  },
  {
    "header": "21879ee25 - 2025-11-24 13:14:10 -0600 - 11/24/2025 13:14:10",
    "grouped": {
      "Added_Other": [
        {
          "name": "FFlagExplorerStreaming3",
          "mechanism": "Enhances the way game assets are loaded and streamed.",
          "purpose": "Reduces loading times and improves the overall experience while exploring games.",
          "freq": 2,
          "old_value": null,
          "new_value": "True"
        },
        {
          "name": "FFlagExpUseCorrectReconcileFunction_Staged",
          "mechanism": "Utilizes an improved function for syncing game states.",
          "purpose": "Ensures a smoother and more accurate gameplay experience for players.",
          "freq": 4,
          "old_value": null,
          "new_value": "true;SteadyState;10;15;Rollout;100;30;SteadyState;100;15;Promote;true;615929293;2025-11-24T19:10:54"
        }
      ],
      "Changed_Other": [
        {
          "name": "DFStringFlagRepoGitHashDynamicString",
          "mechanism": "Links to a dynamic string that reflects the current version of the code.",
          "purpose": "Ensures players benefit from the latest updates and fixes in the game.",
          "freq": 199,
          "old_value": "9409e34be9057cedacdc09f9d73c197e3b6b8044",
          "new_value": "485eea24389628f3c55725338dcaf95671efed56"
        },
        {
          "name": "DFStringFlipTimeStampDynamicString",
          "mechanism": "Adjusts the way timestamps are displayed in dynamic strings.",
          "purpose": "Improves the clarity and accuracy of time-related information for players.",
          "freq": 199,
          "old_value": "11/24/2025 19:07:14",
          "new_value": "11/24/2025 19:13:22"
        },
        {
          "name": "FStringFlagRepoGitHashFastString",
          "mechanism": "Stores a fast string representation of the Git hash for version control.",
          "purpose": "Improves the speed of accessing version information for developers.",
          "freq": 199,
          "old_value": "9409e34be9057cedacdc09f9d73c197e3b6b8044",
          "new_value": "485eea24389628f3c55725338dcaf95671efed56"
        },
        {
          "name": "FStringFlipTimeStampFastString",
          "mechanism": "Optimizes how timestamps are formatted and displayed.",
          "purpose": "Provides faster and more accurate time displays in the game.",
          "freq": 199,
          "old_value": "11/24/2025 19:07:14",
          "new_value": "11/24/2025 19:13:22"
        }
      ],
      "Removed_Other": [
        {
          "name": "FFlagExplorerStreaming3_Staged",
          "mechanism": "Implements a new system for streaming game assets in the Explorer.",
          "purpose": "Enhances performance and loading times for players by optimizing asset management.",
          "freq": 2,
          "old_value": "true;SteadyState;10;15;Rollout;100;30;SteadyState;100;15;Promote;2025-11-24T18:08:51",
          "new_value": null
        }
      ]
    }
  },
  {
    "header": "8fd4ed3ba - 2025-11-24 13:09:44 -0600 - 11/24/2025 13:09:44",
    "grouped": {
      "Added_Camera/UI": [
        {
          "name": "FFlagFFlagAXBuildSubcategoryMapWhenBuildingCategoryInfo",
          "mechanism": "Creates a map of subcategories when generating category information for building.",
          "purpose": "Improves organization and accessibility of building tools for players, making it easier to find what they need.",
          "freq": 1,
          "old_value": null,
          "new_value": "True"
        }
      ],
      "Changed_Other": [
        {
          "name": "DFStringFlagRepoGitHashDynamicString",
          "mechanism": "Links to a dynamic string that reflects the current version of the code.",
          "purpose": "Ensures players benefit from the latest updates and fixes in the game.",
          "freq": 199,
          "old_value": "a71885cdb8d3f25b18ab6fab718cea5870278dac",
          "new_value": "9409e34be9057cedacdc09f9d73c197e3b6b8044"
        },
        {
          "name": "DFStringFlipTimeStampDynamicString",
          "mechanism": "Adjusts the way timestamps are displayed in dynamic strings.",
          "purpose": "Improves the clarity and accuracy of time-related information for players.",
          "freq": 199,
          "old_value": "11/24/2025 19:02:08",
          "new_value": "11/24/2025 19:07:14"
        },
        {
          "name": "FStringFlagRepoGitHashFastString",
          "mechanism": "Stores a fast string representation of the Git hash for version control.",
          "purpose": "Improves the speed of accessing version information for developers.",
          "freq": 199,
          "old_value": "a71885cdb8d3f25b18ab6fab718cea5870278dac",
          "new_value": "9409e34be9057cedacdc09f9d73c197e3b6b8044"
        },
        {
          "name": "FStringFlipTimeStampFastString",
          "mechanism": "Optimizes how timestamps are formatted and displayed.",
          "purpose": "Provides faster and more accurate time displays in the game.",
          "freq": 199,
          "old_value": "11/24/2025 19:02:08",
          "new_value": "11/24/2025 19:07:14"
        }
      ],
      "Removed_Camera/UI": [
        {
          "name": "FFlagFFlagAXBuildSubcategoryMapWhenBuildingCategoryInfo_Staged",
          "mechanism": "Updates the way subcategories are organized in the building category.",
          "purpose": "Helps players find building tools more easily.",
          "freq": 2,
          "old_value": "true;SteadyState;10;15;Rollout;100;30;SteadyState;100;15;Promote;2025-11-24T18:01:46",
          "new_value": null
        }
      ]
    }
  },
  {
    "header": "99c9552cc - 2025-11-24 13:02:56 -0600 - 11/24/2025 13:02:56",
    "grouped": {
      "Changed_Other": [
        {
          "name": "DFStringFlagRepoGitHashDynamicString",
          "mechanism": "Links to a dynamic string that reflects the current version of the code.",
          "purpose": "Ensures players benefit from the latest updates and fixes in the game.",
          "freq": 199,
          "old_value": "674b00b048cbaa6de26544863292fd290b5be008",
          "new_value": "a71885cdb8d3f25b18ab6fab718cea5870278dac"
        },
        {
          "name": "DFStringFlipTimeStampDynamicString",
          "mechanism": "Adjusts the way timestamps are displayed in dynamic strings.",
          "purpose": "Improves the clarity and accuracy of time-related information for players.",
          "freq": 199,
          "old_value": "11/24/2025 18:58:56",
          "new_value": "11/24/2025 19:02:08"
        },
        {
          "name": "FStringFlagRepoGitHashFastString",
          "mechanism": "Stores a fast string representation of the Git hash for version control.",
          "purpose": "Improves the speed of accessing version information for developers.",
          "freq": 199,
          "old_value": "674b00b048cbaa6de26544863292fd290b5be008",
          "new_value": "a71885cdb8d3f25b18ab6fab718cea5870278dac"
        },
        {
          "name": "FStringFlipTimeStampFastString",
          "mechanism": "Optimizes how timestamps are formatted and displayed.",
          "purpose": "Provides faster and more accurate time displays in the game.",
          "freq": 199,
          "old_value": "11/24/2025 18:58:56",
          "new_value": "11/24/2025 19:02:08"
        }
      ]
    }
  },
  {
    "header": "8fb29bf01 - 2025-11-24 13:00:38 -0600 - 11/24/2025 13:00:38",
    "grouped": {
      "Changed_Other": [
        {
          "name": "DFStringFlagRepoGitHashDynamicString",
          "mechanism": "Links to a dynamic string that reflects the current version of the code.",
          "purpose": "Ensures players benefit from the latest updates and fixes in the game.",
          "freq": 199,
          "old_value": "9c6ab15b8d741b93bffc3eb3ff18de3a898e30ef",
          "new_value": "674b00b048cbaa6de26544863292fd290b5be008"
        },
        {
          "name": "DFStringFlipTimeStampDynamicString",
          "mechanism": "Adjusts the way timestamps are displayed in dynamic strings.",
          "purpose": "Improves the clarity and accuracy of time-related information for players.",
          "freq": 199,
          "old_value": "11/24/2025 18:58:06",
          "new_value": "11/24/2025 18:58:56"
        },
        {
          "name": "FStringFlagRepoGitHashFastString",
          "mechanism": "Stores a fast string representation of the Git hash for version control.",
          "purpose": "Improves the speed of accessing version information for developers.",
          "freq": 199,
          "old_value": "9c6ab15b8d741b93bffc3eb3ff18de3a898e30ef",
          "new_value": "674b00b048cbaa6de26544863292fd290b5be008"
        },
        {
          "name": "FStringFlipTimeStampFastString",
          "mechanism": "Optimizes how timestamps are formatted and displayed.",
          "purpose": "Provides faster and more accurate time displays in the game.",
          "freq": 199,
          "old_value": "11/24/2025 18:58:06",
          "new_value": "11/24/2025 18:58:56"
        }
      ]
    }
  },
  {
    "header": "85b8950f9 - 2025-11-24 12:58:20 -0600 - 11/24/2025 12:58:20",
    "grouped": {
      "Changed_Other": [
        {
          "name": "DFStringFlagRepoGitHashDynamicString",
          "mechanism": "Links to a dynamic string that reflects the current version of the code.",
          "purpose": "Ensures players benefit from the latest updates and fixes in the game.",
          "freq": 199,
          "old_value": "e6e88e9f97dafb11382c13f8aecfd678aa94eed2",
          "new_value": "9c6ab15b8d741b93bffc3eb3ff18de3a898e30ef"
        },
        {
          "name": "DFStringFlipTimeStampDynamicString",
          "mechanism": "Adjusts the way timestamps are displayed in dynamic strings.",
          "purpose": "Improves the clarity and accuracy of time-related information for players.",
          "freq": 199,
          "old_value": "11/24/2025 18:55:05",
          "new_value": "11/24/2025 18:58:06"
        },
        {
          "name": "FStringFlagRepoGitHashFastString",
          "mechanism": "Stores a fast string representation of the Git hash for version control.",
          "purpose": "Improves the speed of accessing version information for developers.",
          "freq": 199,
          "old_value": "e6e88e9f97dafb11382c13f8aecfd678aa94eed2",
          "new_value": "9c6ab15b8d741b93bffc3eb3ff18de3a898e30ef"
        },
        {
          "name": "FStringFlipTimeStampFastString",
          "mechanism": "Optimizes how timestamps are formatted and displayed.",
          "purpose": "Provides faster and more accurate time displays in the game.",
          "freq": 199,
          "old_value": "11/24/2025 18:55:05",
          "new_value": "11/24/2025 18:58:06"
        }
      ]
    }
  },
  {
    "header": "87959366a - 2025-11-24 12:56:03 -0600 - 11/24/2025 12:56:03",
    "grouped": {
      "Changed_Other": [
        {
          "name": "DFStringFlagRepoGitHashDynamicString",
          "mechanism": "Links to a dynamic string that reflects the current version of the code.",
          "purpose": "Ensures players benefit from the latest updates and fixes in the game.",
          "freq": 199,
          "old_value": "eb8f36c5a8b40b95753b0b7554bbce9c0bf0e703",
          "new_value": "e6e88e9f97dafb11382c13f8aecfd678aa94eed2"
        },
        {
          "name": "DFStringFlipTimeStampDynamicString",
          "mechanism": "Adjusts the way timestamps are displayed in dynamic strings.",
          "purpose": "Improves the clarity and accuracy of time-related information for players.",
          "freq": 199,
          "old_value": "11/24/2025 18:52:21",
          "new_value": "11/24/2025 18:55:05"
        },
        {
          "name": "FStringFlagRepoGitHashFastString",
          "mechanism": "Stores a fast string representation of the Git hash for version control.",
          "purpose": "Improves the speed of accessing version information for developers.",
          "freq": 199,
          "old_value": "eb8f36c5a8b40b95753b0b7554bbce9c0bf0e703",
          "new_value": "e6e88e9f97dafb11382c13f8aecfd678aa94eed2"
        },
        {
          "name": "FStringFlipTimeStampFastString",
          "mechanism": "Optimizes how timestamps are formatted and displayed.",
          "purpose": "Provides faster and more accurate time displays in the game.",
          "freq": 199,
          "old_value": "11/24/2025 18:52:21",
          "new_value": "11/24/2025 18:55:05"
        }
      ]
    }
  },
  {
    "header": "36a29eb72 - 2025-11-24 12:53:41 -0600 - 11/24/2025 12:53:41",
    "grouped": {
      "Added_Other": [
        {
          "name": "FStringSessionDataInclusionInHttpHeaders_Staged",
          "mechanism": "Includes session data in HTTP headers for better tracking.",
          "purpose": "Enhances security and user experience by ensuring that session information is consistently managed.",
          "freq": 2,
          "old_value": null,
          "new_value": "Home,Games,AvatarExperienceRoot,Chat,More,Landing,Startup,PlayingGame;SteadyState;10;15;Rollout;100;30;SteadyState;100;15;Promote;2025-11-24T18:50:32"
        }
      ],
      "Changed_Other": [
        {
          "name": "DFStringFlagRepoGitHashDynamicString",
          "mechanism": "Links to a dynamic string that reflects the current version of the code.",
          "purpose": "Ensures players benefit from the latest updates and fixes in the game.",
          "freq": 199,
          "old_value": "fe0c0a82051ddbdc042af8400c7886d08ab64d40",
          "new_value": "eb8f36c5a8b40b95753b0b7554bbce9c0bf0e703"
        },
        {
          "name": "DFStringFlipTimeStampDynamicString",
          "mechanism": "Adjusts the way timestamps are displayed in dynamic strings.",
          "purpose": "Improves the clarity and accuracy of time-related information for players.",
          "freq": 199,
          "old_value": "11/24/2025 18:50:57",
          "new_value": "11/24/2025 18:52:21"
        },
        {
          "name": "FFlagFlagRolloutTestStaticBool44",
          "mechanism": "Activates another feature toggle for experimental testing.",
          "purpose": "Helps developers experiment with new features safely.",
          "freq": 1,
          "old_value": "False",
          "new_value": "True"
        },
        {
          "name": "FStringFlagRepoGitHashFastString",
          "mechanism": "Stores a fast string representation of the Git hash for version control.",
          "purpose": "Improves the speed of accessing version information for developers.",
          "freq": 199,
          "old_value": "fe0c0a82051ddbdc042af8400c7886d08ab64d40",
          "new_value": "eb8f36c5a8b40b95753b0b7554bbce9c0bf0e703"
        },
        {
          "name": "FStringFlipTimeStampFastString",
          "mechanism": "Optimizes how timestamps are formatted and displayed.",
          "purpose": "Provides faster and more accurate time displays in the game.",
          "freq": 199,
          "old_value": "11/24/2025 18:50:57",
          "new_value": "11/24/2025 18:52:21"
        }
      ],
      "Removed_Other": [
        {
          "name": "FFlagFlagRolloutTestStaticBool44_Staged",
          "mechanism": "Tests a specific feature by toggling a boolean value during development.",
          "purpose": "Allows players to experience new features before they are fully released.",
          "freq": 2,
          "old_value": "true;SteadyState;10;15;Rollout;100;30;SteadyState;100;15;Promote;2025-11-24T17:50:44",
          "new_value": null
        }
      ]
    }
  },
  {
    "header": "f41ff9f33 - 2025-11-24 12:51:23 -0600 - 11/24/2025 12:51:23",
    "grouped": {
      "Changed_Other": [
        {
          "name": "DFStringFlagRepoGitHashDynamicString",
          "mechanism": "Links to a dynamic string that reflects the current version of the code.",
          "purpose": "Ensures players benefit from the latest updates and fixes in the game.",
          "freq": 199,
          "old_value": "0f948cd526828a078d96b909db44cc7f3758c6f5",
          "new_value": "fe0c0a82051ddbdc042af8400c7886d08ab64d40"
        },
        {
          "name": "DFStringFlipTimeStampDynamicString",
          "mechanism": "Adjusts the way timestamps are displayed in dynamic strings.",
          "purpose": "Improves the clarity and accuracy of time-related information for players.",
          "freq": 199,
          "old_value": "11/24/2025 18:48:34",
          "new_value": "11/24/2025 18:50:57"
        },
        {
          "name": "FStringFlagRepoGitHashFastString",
          "mechanism": "Stores a fast string representation of the Git hash for version control.",
          "purpose": "Improves the speed of accessing version information for developers.",
          "freq": 199,
          "old_value": "0f948cd526828a078d96b909db44cc7f3758c6f5",
          "new_value": "fe0c0a82051ddbdc042af8400c7886d08ab64d40"
        },
        {
          "name": "FStringFlipTimeStampFastString",
          "mechanism": "Optimizes how timestamps are formatted and displayed.",
          "purpose": "Provides faster and more accurate time displays in the game.",
          "freq": 199,
          "old_value": "11/24/2025 18:48:34",
          "new_value": "11/24/2025 18:50:57"
        }
      ]
    }
  },
  {
    "header": "1a32d73f5 - 2025-11-24 12:49:05 -0600 - 11/24/2025 12:49:05",
    "grouped": {
      "Changed_Other": [
        {
          "name": "DFStringFlagRepoGitHashDynamicString",
          "mechanism": "Links to a dynamic string that reflects the current version of the code.",
          "purpose": "Ensures players benefit from the latest updates and fixes in the game.",
          "freq": 199,
          "old_value": "809b7563fca4d337bbe2410e20cbe2ecad19a572",
          "new_value": "0f948cd526828a078d96b909db44cc7f3758c6f5"
        },
        {
          "name": "DFStringFlipTimeStampDynamicString",
          "mechanism": "Adjusts the way timestamps are displayed in dynamic strings.",
          "purpose": "Improves the clarity and accuracy of time-related information for players.",
          "freq": 199,
          "old_value": "11/24/2025 18:46:13",
          "new_value": "11/24/2025 18:48:34"
        },
        {
          "name": "FStringFlagRepoGitHashFastString",
          "mechanism": "Stores a fast string representation of the Git hash for version control.",
          "purpose": "Improves the speed of accessing version information for developers.",
          "freq": 199,
          "old_value": "809b7563fca4d337bbe2410e20cbe2ecad19a572",
          "new_value": "0f948cd526828a078d96b909db44cc7f3758c6f5"
        },
        {
          "name": "FStringFlipTimeStampFastString",
          "mechanism": "Optimizes how timestamps are formatted and displayed.",
          "purpose": "Provides faster and more accurate time displays in the game.",
          "freq": 199,
          "old_value": "11/24/2025 18:46:13",
          "new_value": "11/24/2025 18:48:34"
        }
      ],
      "Removed_Other": [
        {
          "name": "FFlagExpChatReconcileOnAgeVerifiedChange_Staged",
          "mechanism": "Updates chat settings when a player's age verification status changes.",
          "purpose": "Ensures that chat features are appropriate and safe based on player age.",
          "freq": 4,
          "old_value": "true;SteadyState;10;15;Rollout;100;30;SteadyState;100;15;Promote;true;1736074955;2025-11-24T18:29:45",
          "new_value": null
        },
        {
          "name": "FFlagExpUseCorrectReconcileFunction_Staged",
          "mechanism": "Utilizes an improved function for syncing game states.",
          "purpose": "Ensures a smoother and more accurate gameplay experience for players.",
          "freq": 4,
          "old_value": "true;SteadyState;10;15;Rollout;100;30;SteadyState;100;15;Promote;true;1736074955;2025-11-24T18:29:45",
          "new_value": null
        }
      ]
    }
  }
]